odoo/addons/resource_hook/README.rst
odoo/addons/resource_hook/__init__.py
odoo/addons/resource_hook/__manifest__.py
odoo/addons/resource_hook/hooks.py
odoo/addons/resource_hook/i18n/resource_hook.pot
odoo/addons/resource_hook/models/__init__.py
odoo/addons/resource_hook/models/resource_calendar.py
odoo/addons/resource_hook/models/resource_mixin.py
odoo/addons/resource_hook/readme/CONTRIBUTORS.rst
odoo/addons/resource_hook/readme/DESCRIPTION.rst
odoo/addons/resource_hook/readme/HISTORY.rst
odoo/addons/resource_hook/static/description/icon.png
odoo/addons/resource_hook/static/description/index.html
odoo12_addon_resource_hook-12.0.1.0.2.dist-info/METADATA
odoo12_addon_resource_hook-12.0.1.0.2.dist-info/WHEEL
odoo12_addon_resource_hook-12.0.1.0.2.dist-info/top_level.txt
odoo12_addon_resource_hook-12.0.1.0.2.dist-info/RECORD
